bunnet/__init__.py
bunnet/exceptions.py
bunnet/operators.py
bunnet/py.typed
bunnet/pydantic_check.py
bunnet/executors/__init__.py
bunnet/executors/migrate.py
bunnet/migrations/__init__.py
bunnet/migrations/database.py
bunnet/migrations/models.py
bunnet/migrations/runner.py
bunnet/migrations/template.py
bunnet/migrations/utils.py
bunnet/migrations/controllers/__init__.py
bunnet/migrations/controllers/base.py
bunnet/migrations/controllers/free_fall.py
bunnet/migrations/controllers/iterative.py
bunnet/odm/__init__.py
bunnet/odm/actions.py
bunnet/odm/bulk.py
bunnet/odm/cache.py
bunnet/odm/documents.py
bunnet/odm/enums.py
bunnet/odm/fields.py
bunnet/odm/models.py
bunnet/odm/registry.py
bunnet/odm/union_doc.py
bunnet/odm/views.py
bunnet/odm/custom_types/__init__.py
bunnet/odm/custom_types/decimal.py
bunnet/odm/custom_types/bson/__init__.py
bunnet/odm/custom_types/bson/binary.py
bunnet/odm/interfaces/__init__.py
bunnet/odm/interfaces/aggregate.py
bunnet/odm/interfaces/aggregation_methods.py
bunnet/odm/interfaces/clone.py
bunnet/odm/interfaces/detector.py
bunnet/odm/interfaces/find.py
bunnet/odm/interfaces/getters.py
bunnet/odm/interfaces/inheritance.py
bunnet/odm/interfaces/run.py
bunnet/odm/interfaces/session.py
bunnet/odm/interfaces/setters.py
bunnet/odm/interfaces/update.py
bunnet/odm/operators/__init__.py
bunnet/odm/operators/find/__init__.py
bunnet/odm/operators/find/array.py
bunnet/odm/operators/find/bitwise.py
bunnet/odm/operators/find/comparison.py
bunnet/odm/operators/find/element.py
bunnet/odm/operators/find/evaluation.py
bunnet/odm/operators/find/geospatial.py
bunnet/odm/operators/find/logical.py
bunnet/odm/operators/update/__init__.py
bunnet/odm/operators/update/array.py
bunnet/odm/operators/update/bitwise.py
bunnet/odm/operators/update/general.py
bunnet/odm/queries/__init__.py
bunnet/odm/queries/aggregation.py
bunnet/odm/queries/cursor.py
bunnet/odm/queries/delete.py
bunnet/odm/queries/find.py
bunnet/odm/queries/update.py
bunnet/odm/settings/__init__.py
bunnet-1.3.0.dist-info/entry_points.txt
bunnet-1.3.0.dist-info/LICENSE
bunnet-1.3.0.dist-info/WHEEL
bunnet-1.3.0.dist-info/METADATA
bunnet-1.3.0.dist-info/RECORD
